cheml/__init__.py
cheml/find_fragments.py
cheml/fragments_library.py
cheml/smiles_to_structure.py
cheml/structure_to_smiles.py
cheml-0.0.2.dist-info/LICENSE
cheml-0.0.2.dist-info/METADATA
cheml-0.0.2.dist-info/WHEEL
cheml-0.0.2.dist-info/top_level.txt
cheml-0.0.2.dist-info/RECORD
